{
  "Lambda": 332.0,
  "alpha_inv_bare": 137.036,
  "running": [
    {
      "N": 1,
      "Q_MeV": 332.0,
      "ratio_32": 0.5119561945,
      "ratio_1024": 0.3406127321,
      "alpha_inv": 205.9712
    },
    {
      "N": 2,
      "Q_MeV": 481.7,
      "ratio_32": 0.5116848833,
      "ratio_1024": 0.3373625603,
      "alpha_inv": 207.8454
    },
    {
      "N": 3,
      "Q_MeV": 698.9,
      "ratio_32": 0.5116846979,
      "ratio_1024": 0.3373074625,
      "alpha_inv": 207.8793
    },
    {
      "N": 4,
      "Q_MeV": 1014.1,
      "ratio_32": 0.5116846978,
      "ratio_1024": 0.3373064864,
      "alpha_inv": 207.8799
    },
    {
      "N": 6,
      "Q_MeV": 2135.0,
      "ratio_32": 0.5116846978,
      "ratio_1024": 0.3373064687,
      "alpha_inv": 207.8799
    },
    {
      "N": 8,
      "Q_MeV": 4494.6,
      "ratio_32": 0.5116846978,
      "ratio_1024": 0.3373064687,
      "alpha_inv": 207.8799
    },
    {
      "N": 12,
      "Q_MeV": 19920.0,
      "ratio_32": 0.5116846978,
      "ratio_1024": 0.3373064687,
      "alpha_inv": 207.8799
    },
    {
      "N": 16,
      "Q_MeV": 88285.6,
      "ratio_32": 0.5116846978,
      "ratio_1024": 0.3373064687,
      "alpha_inv": 207.8799
    },
    {
      "N": 24,
      "Q_MeV": 1734166.1,
      "ratio_32": 0.5116846978,
      "ratio_1024": 0.3373064687,
      "alpha_inv": 207.8799
    },
    {
      "N": 32,
      "Q_MeV": 34063683.4,
      "ratio_32": 0.5116846978,
      "ratio_1024": 0.3373064687,
      "alpha_inv": 207.8799
    },
    {
      "N": 64,
      "Q_MeV": 5071019084476.1,
      "ratio_32": 0.5116846978,
      "ratio_1024": 0.3373064687,
      "alpha_inv": 207.8799
    }
  ]
}